LICENCE
README.md
setup.cfg
setup.py
django_labeltree.egg-info/PKG-INFO
django_labeltree.egg-info/SOURCES.txt
django_labeltree.egg-info/dependency_links.txt
django_labeltree.egg-info/requires.txt
django_labeltree.egg-info/top_level.txt
labeltree/__init__.py
labeltree/admin.py
labeltree/apps.py
labeltree/tests.py
labeltree/urls.py
labeltree/views.py
labeltree/management/__init__.py
labeltree/management/commands/__init__.py
labeltree/management/commands/addgroups.py
labeltree/management/commands/addlabels.py
labeltree/management/commands/gbif_api.py
labeltree/management/commands/listlabels.py
labeltree/management/commands/search.py
labeltree/management/commands/translate_to_scientific.py
labeltree/migrations/0001_initial.py
labeltree/migrations/0002_alter_label_unique_together_alter_label_kr_nr_and_more.py
labeltree/migrations/0003_labelgroup.py
labeltree/migrations/0004_alter_label_taxonomic_rank.py
labeltree/migrations/__init__.py
labeltree/models/__init__.py
labeltree/models/base.py
labeltree/models/label.py
labeltree/models/label_group.py